flexi_hash_embedding/__init__.py
flexi_hash_embedding/flexi_hash_embedding.py
flexi_hash_embedding-0.0.3.dist-info/LICENSE
flexi_hash_embedding-0.0.3.dist-info/METADATA
flexi_hash_embedding-0.0.3.dist-info/WHEEL
flexi_hash_embedding-0.0.3.dist-info/top_level.txt
flexi_hash_embedding-0.0.3.dist-info/RECORD
