Metadata-Version: 2.1
Name: flexi-hash-embedding
Version: 0.0.3
Summary: PyTorch Extension Library of Optimized Scatter Operations
Home-page: https://github.com/cemoody/flexi_hash_embedding
Author: Christopher Moody
Author-email: chrisemoody@gmail.com
License: UNKNOWN
Download-URL: https://github.com/cemoody/flexi_hash_embedding/archive/0.0.3.tar.gz
Keywords: pytorch,scatter,groupby,embedding,hashing,variable,fixed
Platform: UNKNOWN
Classifier: Programming Language :: Python :: 3
Classifier: License :: OSI Approved :: MIT License
Classifier: Operating System :: OS Independent
Requires-Dist: torch
Requires-Dist: torch-scatter
Requires-Dist: sklearn
